xiyan_mcp_server/__init__.py
xiyan_mcp_server/__main__.py
xiyan_mcp_server/config_demo.yml
xiyan_mcp_server/database_env.py
xiyan_mcp_server/server.py
xiyan_mcp_server/local_model/README.md
xiyan_mcp_server/local_model/local_xiyan_server.py
xiyan_mcp_server/utils/common_util.py
xiyan_mcp_server/utils/db_config.py
xiyan_mcp_server/utils/db_mschema.py
xiyan_mcp_server/utils/db_source.py
xiyan_mcp_server/utils/db_util.py
xiyan_mcp_server/utils/file_util.py
xiyan_mcp_server/utils/llm_util.py
xiyan_mcp_server/utils/logger_util.py
xiyan_mcp_server-0.1.7.dist-info/METADATA
xiyan_mcp_server-0.1.7.dist-info/WHEEL
xiyan_mcp_server-0.1.7.dist-info/entry_points.txt
xiyan_mcp_server-0.1.7.dist-info/licenses/LICENSE.txt
xiyan_mcp_server-0.1.7.dist-info/RECORD
